LICENSE
MANIFEST.in
README.md
setup.py
pampio/__init__.py
pampio/ampioip.py
pampio/base.py
pampio/frame.py
pampio/utils.py
pampio/version.py
pampio.egg-info/PKG-INFO
pampio.egg-info/SOURCES.txt
pampio.egg-info/dependency_links.txt
pampio.egg-info/not-zip-safe
pampio.egg-info/top_level.txt
tests/__init__.py
tests/unit/__init__.py
tests/unit/test_crc.py